[{"nombre":"Primer Domingo","comentarios":"Este es el primer domingo del mes de marzo","fecha":"2023-01-05","irrenunciable":"0","tipo":"Domingo"},{"nombre":"Segundo Domingp","comentarios":"Este es el segundo domingo del mes de marzo","fecha":"2023-01-12","irrenunciable":"0","tipo":"Domingo"},{"nombre":"Tercer Domingo","comentarios":"Este es el tercer domingo del mes de marzo","fecha":"2023-01-19","irrenunciable":"0","tipo":"Domingp"},{"nombre":"Cuarto Domingo","comentarios":"Este es el cuarto domingo del mes de marzo","fecha":"2023-01-26","irrenunciable":"0","tipo":"Domingo"}]